llama_index/llms/solar/__init__.py
llama_index/llms/solar/base.py
llama_index_llms_solar-0.3.1.dist-info/METADATA
llama_index_llms_solar-0.3.1.dist-info/WHEEL
llama_index_llms_solar-0.3.1.dist-info/RECORD
